easy_dna/__init__.py
easy_dna/biological_operations.py
easy_dna/biotables.py
easy_dna/enzymes.py
easy_dna/extractor.py
easy_dna/io.py
easy_dna/matching.py
easy_dna/modifications.py
easy_dna/random_sequences.py
easy_dna/record_operations.py
easy_dna/version.py
easy_dna/data/README.md
easy_dna/data/codons_translations.csv
easy_dna/data/complements.csv
easy_dna/data/iupac_notation.csv
easy_dna/data/nucleotide_to_regexpr.csv
easy_dna-0.4.1.dist-info/licenses/LICENSE
easy_dna-0.4.1.dist-info/METADATA
easy_dna-0.4.1.dist-info/WHEEL
easy_dna-0.4.1.dist-info/top_level.txt
easy_dna-0.4.1.dist-info/RECORD
