Metadata-Version: 2.4
Name: easy_dna
Version: 0.4.1
Summary: Methods for DNA sequence reading, writing and editing.
Author: Zulko
License-Expression: MIT
Project-URL: Homepage, https://github.com/Edinburgh-Genome-Foundry/easy_dna
Keywords: DNA,sequence,Genbank,record,editing
License-File: LICENSE
Requires-Dist: numpy
Requires-Dist: Biopython
Requires-Dist: snapgene_reader
Requires-Dist: flametree
Requires-Dist: pandas
Requires-Dist: crazydoc
Dynamic: license-file
